[{"id": 3170558}, {"project_id": 124084}, {"name": "IT: Breeze: Testing Python script"}, {"description": "Testing if the python script can easily post to breeze"}, {"position": 16}, {"stage_id": 146483}, {"color": null}, {"duedate": "2020-03-22"}, {"startdate": "2020-02-09"}, {"created_at": "2020-02-09"}, {"swimlane_id": 1}, {"planned_time": 30}, {"user": [{"id": 56539}, {"email": "paulg@bungalow5.com"}, {"name": "Paul Gilfoy"}]}, {"users": [{"id": 56539}, {"email": "paulg@bungalow5.com"}, {"name": "Paul Gilfoy"}]}]